{
    "#nodes":20,
    "#links":55,
    "links":[
        {
            "source":"北京南",
            "target":"天津",
            "weight":161
        },
        {
            "source":"北京南",
            "target":"上海",
            "weight":6
        },
        {
            "source":"北京南",
            "target":"上海虹桥",
            "weight":78
        },
        {
            "source":"北京南",
            "target":"福州",
            "weight":8
        },
        {
            "source":"北京南",
            "target":"合肥南",
            "weight":10
        },
        {
            "source":"北京南",
            "target":"哈尔滨西",
            "weight":18
        },
        {
            "source":"天津",
            "target":"长沙南",
            "weight":2
        },
        {
            "source":"上海南",
            "target":"金山卫",
            "weight":144
        },
        {
            "source":"武汉",
            "target":"成都东",
            "weight":2
        },
        {
            "source":"武汉",
            "target":"重庆北",
            "weight":2
        },
        {
            "source":"武汉",
            "target":"上海虹桥",
            "weight":9
        },
        {
            "source":"武汉",
            "target":"福州",
            "weight":2
        },
        {
            "source":"武汉",
            "target":"深圳北",
            "weight":24
        },
        {
            "source":"武汉",
            "target":"北京西",
            "weight":19
        },
        {
            "source":"武汉",
            "target":"西安北",
            "weight":2
        },
        {
            "source":"武汉",
            "target":"广州南",
            "weight":51
        },
        {
            "source":"武汉",
            "target":"哈尔滨西",
            "weight":2
        },
        {
            "source":"武汉",
            "target":"贵阳北",
            "weight":4
        },
        {
            "source":"成都东",
            "target":"上海虹桥",
            "weight":6
        },
        {
            "source":"成都东",
            "target":"福州",
            "weight":2
        },
        {
            "source":"成都东",
            "target":"重庆北",
            "weight":62
        },
        {
            "source":"成都东",
            "target":"北京西",
            "weight":2
        },
        {
            "source":"成都东",
            "target":"广州南",
            "weight":4
        },
        {
            "source":"贵阳北",
            "target":"广州南",
            "weight":38
        },
        {
            "source":"贵阳北",
            "target":"北京西",
            "weight":6
        },
        {
            "source":"贵阳北",
            "target":"上海虹桥",
            "weight":14
        },
        {
            "source":"贵阳北",
            "target":"长沙南",
            "weight":8
        },
        {
            "source":"贵阳北",
            "target":"深圳北",
            "weight":2
        },
        {
            "source":"深圳北",
            "target":"北京西",
            "weight":12
        },
        {
            "source":"深圳北",
            "target":"上海虹桥",
            "weight":12
        },
        {
            "source":"深圳北",
            "target":"福州",
            "weight":2
        },
        {
            "source":"深圳北",
            "target":"西安北",
            "weight":6
        },
        {
            "source":"深圳北",
            "target":"重庆北",
            "weight":2
        },
        {
            "source":"深圳北",
            "target":"合肥南",
            "weight":2
        },
        {
            "source":"深圳北",
            "target":"长沙南",
            "weight":22
        },
        {
            "source":"深圳北",
            "target":"广州南",
            "weight":50
        },
        {
            "source":"深圳",
            "target":"广州东",
            "weight":135
        },
        {
            "source":"广州南",
            "target":"北京西",
            "weight":10
        },
        {
            "source":"广州南",
            "target":"上海虹桥",
            "weight":16
        },
        {
            "source":"广州南",
            "target":"西安北",
            "weight":10
        },
        {
            "source":"广州南",
            "target":"合肥南",
            "weight":2
        },
        {
            "source":"广州南",
            "target":"长沙南",
            "weight":18
        },
        {
            "source":"哈尔滨西",
            "target":"上海虹桥",
            "weight":2
        },
        {
            "source":"上海虹桥",
            "target":"重庆北",
            "weight":4
        },
        {
            "source":"上海虹桥",
            "target":"福州",
            "weight":12
        },
        {
            "source":"上海虹桥",
            "target":"合肥南",
            "weight":9
        },
        {
            "source":"上海虹桥",
            "target":"长沙南",
            "weight":29
        },
        {
            "source":"福州",
            "target":"重庆北",
            "weight":2
        },
        {
            "source":"福州",
            "target":"长沙南",
            "weight":2
        },
        {
            "source":"福州",
            "target":"合肥南",
            "weight":2
        },
        {
            "source":"西安北",
            "target":"上海",
            "weight":4
        },
        {
            "source":"西安北",
            "target":"北京西",
            "weight":26
        },
        {
            "source":"上海",
            "target":"合肥南",
            "weight":21
        },
        {
            "source":"重庆北",
            "target":"北京西",
            "weight":2
        },
        {
            "source":"北京西",
            "target":"长沙南",
            "weight":8
        }
    ],
    "node_list":[
        "北京南",
        "天津",
        "上海南",
        "金山卫",
        "武汉",
        "成都东",
        "贵阳北",
        "深圳北",
        "深圳",
        "广州东",
        "广州南",
        "哈尔滨西",
        "上海虹桥",
        "福州",
        "西安北",
        "上海",
        "重庆北",
        "北京西",
        "长沙南",
        "合肥南"
    ],
    "#nodesorigin":0,
    "#edgesorigin":0
}